setup.py
django_dropbox/__init__.py
django_dropbox/models.py
django_dropbox/settings.py
django_dropbox/storage.py
django_dropbox/tests.py
django_dropbox/views.py
django_dropbox_redux.egg-info/PKG-INFO
django_dropbox_redux.egg-info/SOURCES.txt
django_dropbox_redux.egg-info/dependency_links.txt
django_dropbox_redux.egg-info/requires.txt
django_dropbox_redux.egg-info/top_level.txt