Metadata-Version: 1.0
Name: django-dropbox-redux
Version: 0.0.5
Summary: A Django App that contains a Django Storage which uses Dropbox with Python3 support.
Home-page: https://github.com/daikeren/django-dropbox
Author: Ke-Ren Dai
Author-email: daikeren@gmail.com
License: UNKNOWN
Platform: UNKNOWN
